ragstack_colbert/__init__.py
ragstack_colbert/base_database.py
ragstack_colbert/base_embedding_model.py
ragstack_colbert/base_retriever.py
ragstack_colbert/base_vector_store.py
ragstack_colbert/cassandra_database.py
ragstack_colbert/colbert_embedding_model.py
ragstack_colbert/colbert_retriever.py
ragstack_colbert/colbert_vector_store.py
ragstack_colbert/constant.py
ragstack_colbert/objects.py
ragstack_colbert/py.typed
ragstack_colbert/text_encoder.py
ragstack_ai_colbert-1.0.6.dist-info/METADATA
ragstack_ai_colbert-1.0.6.dist-info/WHEEL
ragstack_ai_colbert-1.0.6.dist-info/RECORD
